mantis_authz/__init__.py
mantis_authz/api.py
mantis_authz/backoffice/__init__.py
mantis_authz/backoffice/api.py
mantis_authz/backoffice/self.py
mantis_authz/cache.py
mantis_authz/config.py
mantis_authz/models.py
mantis_authz/opa.py
mantis_authz/util.py
mantis_authz-0.3.4.dist-info/METADATA
mantis_authz-0.3.4.dist-info/WHEEL
mantis_authz-0.3.4.dist-info/RECORD
