Metadata-Version: 2.1
Name: mantis-authz
Version: 0.3.4
Summary: M&NTIS library that provide authorization facilities
License: MIT
Author: AMOSSYS
Requires-Python: >=3.9,<4.0
Classifier: License :: OSI Approved :: MIT License
Classifier: Programming Language :: Python :: 3
Classifier: Programming Language :: Python :: 3.9
Classifier: Programming Language :: Python :: 3.10
Classifier: Programming Language :: Python :: 3.11
Classifier: Programming Language :: Python :: 3.12
Classifier: Programming Language :: Python :: 3.13
Requires-Dist: aiohttp (>=3.8.1,<4.0.0)
Requires-Dist: async-lru (>=2.0.5,<3.0.0)
Requires-Dist: fastapi (<1)
Requires-Dist: fastapi-opa (>=2.0.3,<3.0.0)
Requires-Dist: httpx (>=0.10.0,<1.0.0)
Requires-Dist: omegaconf (>=2.2.2,<3.0.0)
Requires-Dist: opa-python-client (>=2.0.2,<3.0.0)
Requires-Dist: python-jose (>=3.3.0,<4.0.0)
Requires-Dist: python-keycloak (>=5.3.1,<6.0.0)
